.VERSION
AUTHORS.rst
CONTRIBUTING.rst
HISTORY.rst
LICENSE
MANIFEST.in
Pipfile
Pipfile.lock
README.rst
USAGE.rst
aws_energy_labeler_cli.py
dev-requirements.txt
requirements.txt
setup.cfg
setup.py
awsenergylabelercli/.VERSION
awsenergylabelercli/AUTHORS.rst
awsenergylabelercli/CONTRIBUTING.rst
awsenergylabelercli/HISTORY.rst
awsenergylabelercli/LICENSE
awsenergylabelercli/Pipfile
awsenergylabelercli/Pipfile.lock
awsenergylabelercli/README.rst
awsenergylabelercli/USAGE.rst
awsenergylabelercli/__init__.py
awsenergylabelercli/_version.py
awsenergylabelercli/awsenergylabelercli.py
awsenergylabelercli/awsenergylabelercliexceptions.py
awsenergylabelercli/dev-requirements.txt
awsenergylabelercli/entities.py
awsenergylabelercli/requirements.txt
awsenergylabelercli/validators.py
awsenergylabelercli.egg-info/PKG-INFO
awsenergylabelercli.egg-info/SOURCES.txt
awsenergylabelercli.egg-info/dependency_links.txt
awsenergylabelercli.egg-info/entry_points.txt
awsenergylabelercli.egg-info/not-zip-safe
awsenergylabelercli.egg-info/requires.txt
awsenergylabelercli.egg-info/top_level.txt
awsenergylabelercli/conf/logging.json-example
docs/Makefile
docs/authors.rst
docs/conf.py
docs/contributing.rst
docs/history.rst
docs/index.rst
docs/installation.rst
docs/readme.rst
docs/usage.rst
tests/test_awsenergylabelercli.py