Metadata-Version: 2.1
Name: awsenergylabelercli
Version: 3.2.1
Summary: A cli to label accounts and landing zones with energy labels based on Security Hub finding.
Home-page: https://github.com/schubergphilis/awsenergylabelercli.git
Author: Theodoor Scholte
Author-email: tscholte@schubergphilis.com
License: MIT
Keywords: awsenergylabelercli energy labeler aws security hub
Classifier: Development Status :: 4 - Beta
Classifier: Intended Audience :: Developers
Classifier: License :: OSI Approved :: MIT License
Classifier: Natural Language :: English
Classifier: Programming Language :: Python :: 3.7
License-File: LICENSE
License-File: AUTHORS.rst
